deepwalk/__init__.py
deepwalk/__main__.py
deepwalk/graph.py
deepwalk/skipgram.py
deepwalk/walks.py
deepwalk-1.0.3.dist-info/METADATA
deepwalk-1.0.3.dist-info/RECORD
deepwalk-1.0.3.dist-info/WHEEL
deepwalk-1.0.3.dist-info/entry_points.txt
deepwalk-1.0.3.dist-info/top_level.txt
