Metadata-Version: 2.1
Name: deepwalk
Version: 1.0.3
Summary: DeepWalk online learning of social representations.
Home-page: https://github.com/phanein/deepwalk
Author: Bryan Perozzi
Author-email: bperozzi@cs.stonybrook.edu
License: GPLv3
Keywords: deepwalk
Platform: UNKNOWN
Classifier: Development Status :: 2 - Pre-Alpha
Classifier: Intended Audience :: Developers
Classifier: License :: OSI Approved :: BSD License
Classifier: Natural Language :: English
Classifier: Programming Language :: Python :: 2
Classifier: Programming Language :: Python :: 2.7
Classifier: Programming Language :: Python :: 3
Classifier: Programming Language :: Python :: 3.4
Requires-Dist: wheel (>=0.23.0)
Requires-Dist: Cython (>=0.20.2)
Requires-Dist: argparse (>=1.2.1)
Requires-Dist: futures (>=2.1.6)
Requires-Dist: six (>=1.7.3)
Requires-Dist: gensim (>=1.0.0)
Requires-Dist: scipy (>=0.15.0)
Requires-Dist: psutil (>=2.1.1)
